{
    "hero": {
        "spawn_point": {
            "location": {
                "x": -400,
                "y": 37.8,
                "z": 0.28
            },
            "rotation": {
                "pitch": 0.0,
                "yaw": -0.368408,
                "roll": 0.0
            }
        },
        "way_points": [
            {
                "x": 300,
                "y": 37.8,
                "z": 0.281942
            },
            {
                "x": -380,
                "y": 37.8,
                "z": 0.281942
            }
        ],
        "target_speed": 25
    },
    "other1": {
        "spawn_point": {
            "location": {
                "x": -325,
                "y": 37.8,
                "z": 0.28
            },
            "rotation": {
                "pitch": 0.0,
                "yaw": -0.368408,
                "roll": 0.0
            }
        },
        "way_points": [
            {
                "x": -320,
                "y": 37.8,
                "z": 0.281942
            },
            {
                "x": 25.7,
                "y": 37.8,
                "z": 0.281942
            },
            {
                "x": 32,
                "y": 33.8,
                "z": 0.281942
            },
            {
                "x": 300,
                "y": 33.8,
                "z": 0.281942
            }
        ],
        "target_speed": 25
    },
    "other2": {
        "spawn_point": {
            "location": {
                "x": 100,
                "y": 37.8,
                "z": 11
            },
            "rotation": {
                "pitch": 0.0,
                "yaw": -0.368408,
                "roll": 0.0
            }
        },
        "way_points": [
            {
                "x": -380,
                "y": 37.8,
                "z": 0.281942
            },
            {
                "x": 300,
                "y": 37.8,
                "z": 0.281942
            }
        ],
        "target_speed": 0
    }
}